HtmlLib/HtmlExtention.py
HtmlLib/HtmlFrame.py
HtmlLib/HtmlWidget.py
HtmlLib/Tool.py
HtmlLib/__init__.py
pyhtmllib-1.1.dist-info/LICENSE
pyhtmllib-1.1.dist-info/METADATA
pyhtmllib-1.1.dist-info/WHEEL
pyhtmllib-1.1.dist-info/top_level.txt
pyhtmllib-1.1.dist-info/zip-safe
pyhtmllib-1.1.dist-info/RECORD
