Metadata-Version: 2.1
Name: pyhtmllib
Version: 1.1
Summary: HtmlLib is a free python package, using to discribe html page with Python.
Home-page: https://gitee.com/albert_zhong/htmllib/tree/master/
Author: PointCode Organization
Author-email: pointcode@126.com
License: Apache-2.0
Keywords: html web front-end
Platform: UNKNOWN
Classifier: Programming Language :: Python
Classifier: Intended Audience :: Developers
Classifier: Operating System :: OS Independent
